cone.ldap-0.2-py3.9-nspkg.pth
cone/ldap/__init__.py
cone/ldap/settings.py
cone/ldap/browser/__init__.py
cone/ldap/browser/settings.py
cone/ldap/browser/forms/groups_settings.yaml
cone/ldap/browser/forms/roles_settings.yaml
cone/ldap/browser/forms/server_settings.yaml
cone/ldap/browser/forms/users_settings.yaml
cone/ldap/browser/static/styles.css
cone/ldap/browser/templates/groups_settings.pt
cone/ldap/browser/templates/roles_settings.pt
cone/ldap/browser/templates/server_settings.pt
cone/ldap/browser/templates/users_settings.pt
cone/ldap/locale/cone.ldap.pot
cone/ldap/locale/de/LC_MESSAGES/cone.ldap.mo
cone/ldap/locale/de/LC_MESSAGES/cone.ldap.po
cone/ldap/locale/en/LC_MESSAGES/cone.ldap.mo
cone/ldap/locale/en/LC_MESSAGES/cone.ldap.po
cone/ldap/testing/__init__.py
cone/ldap/testing/ldap_groups.xml
cone/ldap/testing/ldap_roles.xml
cone/ldap/testing/ldap_server.xml
cone/ldap/testing/ldap_users.xml
cone/ldap/tests/__init__.py
cone/ldap/tests/test_browser_settings.py
cone/ldap/tests/test_ldap.py
cone/ldap/tests/test_settings.py
cone/ldap/tests/test_ugm.py
cone.ldap-0.2.dist-info/LICENSE.rst
cone.ldap-0.2.dist-info/METADATA
cone.ldap-0.2.dist-info/WHEEL
cone.ldap-0.2.dist-info/namespace_packages.txt
cone.ldap-0.2.dist-info/top_level.txt
cone.ldap-0.2.dist-info/RECORD
