Metadata-Version: 2.1
Name: cone.ldap
Version: 0.2
Summary: LDAP integration for cone.app
Home-page: http://github.com/conestack/cone.ldap
Author: Cone Contributors
Author-email: dev@conestack.org
License: Simplified BSD
Platform: UNKNOWN
Classifier: Environment :: Web Environment
Classifier: Programming Language :: Python
Classifier: Topic :: Internet :: WWW/HTTP :: Dynamic Content
Classifier: License :: OSI Approved :: GNU Lesser General Public License v3 (LGPLv3)
Requires-Dist: setuptools
Requires-Dist: node.ext.ldap
Requires-Dist: cone.ugm
Requires-Dist: yafowil.widget.array
Requires-Dist: yafowil.widget.dict
Requires-Dist: yafowil.yaml
Provides-Extra: test
Requires-Dist: lxml ; extra == 'test'
Requires-Dist: yafowil.yaml ; extra == 'test'
Requires-Dist: zope.testrunner ; extra == 'test'
